{
  "project_info": {
    "project_number": "415123239",
    "project_id": "esehat-23a17",
    "storage_bucket": "esehat-23a17.firebasestorage.app"
  },
  "client": [
    {
      "client_info": {
        "mobilesdk_app_id": "1:415123239:android:37f3bab9bb971108a34b02",
        "android_client_info": {
          "package_name": "com.firstapp.esehat"
        }
      },
      "oauth_client": [],
      "api_key": [
        {
          "current_key": "AIzaSyCQf-j_COL3a6vQ5BhUCCQg4tcC4FtQEWs"
        }
      ],
      "services": {
        "appinvite_service": {
          "other_platform_oauth_client": []
        }
      }
    }
  ],
  "configuration_version": "1"
}